topic_modeling_tool/__init__.py
topic_modeling_tool/topic_modeler.py
topic_modeling_tool-0.1.1.dist-info/METADATA
topic_modeling_tool-0.1.1.dist-info/WHEEL
topic_modeling_tool-0.1.1.dist-info/top_level.txt
topic_modeling_tool-0.1.1.dist-info/RECORD
