Metadata-Version: 2.1
Name: topic-modeling-tool
Version: 0.1.1
Summary: A simple topic modeling tool using LDA
Home-page: https://github.com/yourusername/topic_modeling_tool
Author: Takumi Maruyama
Author-email: s2222095@stu.musashino-u.ac.jp
Classifier: Programming Language :: Python :: 3
Classifier: License :: OSI Approved :: MIT License
Classifier: Operating System :: OS Independent
Requires-Python: >=3.6
Requires-Dist: scikit-learn
Requires-Dist: pandas
